{
	"Achad": 7,
	"Ahau": 1,
	"Anomaly": 3,
	"Avalanche": 7,
	"Axeitus Headbanger": 7,
	"Bibby Bloodbath": 2,
	"Black Knight": 17,
	"Black Vixen": 7,
	"Bloodback": 6,
	"Bloodpaw": 7,
	"Bovinus": 7,
	"Colerian the Barbarian": 7,
	"Cursed Gladiator": 7,
	"Custodian": 1,
	"Darakan the Executioner": 6,
	"Darkfang": 6,
	"Deathbine": 14,
	"Deathbringer": 2,
	"Diseased Bill": 11,
	"Diseased Dan": 13,
	"Diseased Fred": 12,
	"Drasilla": 7,
	"Duke Krule": 2,
	"Ekatrix": 1,
	"Esmeralda": 7,
	"Faceless Bane": 6,
	"Fallen Mooh'Tah Master Ghar": 3,
	"Fleshcrawler": 14,
	"Frostfur": 7,
	"Gaffir": 1,
	"Gnorre Chyllson": 4,
	"Grand Master Oberon": 2,
	"Grimgor Guteater": 7,
	"Guard Captain Quaid": 1,
	"Hide": 23,
	"Katex Blood Tongue": 5,
	"Koshei the Deathless": 1,
	"Kreebosh the Exile": 7,
	"Kroazur": 6,
	"Leiden": 2,
	"Leviathan": 1,
	"Mad Mage": 1,
	"Mad Technomancer": 8,
	"Morik the Gladiator": 9,
	"Muglex Clan Chief": 81,
	"Munster": 1,
	"Norgle Glacierbeard": 6,
	"Orcus the Cruel": 7,
	"Raging Mage": 1,
	"Ravenous Hunger": 2,
	"Raxias": 1,
	"Renegade Orc": 2,
	"Ribstride": 9,
	"Rocky": 7,
	"Ron the Ripper": 1,
	"Rottie the Rotworm": 1,
	"Scarlett Etzel": 8,
	"Shadowpelt": 6,
	"Shard of Corruption": 5,
	"Shardhead": 4,
	"Sharpclaw": 6,
	"Sir Valorcrest": 1,
	"Slim": 7,
	"Spirits of Earth": 7,
	"Spirits of Fire": 7,
	"Spirits of Water": 7,
	"Srezz Yellow Eyes": 5,
	"Svoren the Mad": 6,
	"The Bloodtusk": 5,
	"The Bloodweb": 5,
	"The Corruptor": 85,
	"The Count": 3,
	"The Dark Dancer": 7,
	"The Flaming Orchid": 3,
	"The Hag": 7,
	"The Hairy One": 7,
	"The Masked Marauder": 5,
	"The Moonlight Aster": 3,
	"The Obliverator": 2,
	"The Old Widow": 1,
	"The Pit Lord": 6,
	"The Snapper": 10,
	"The Weakened Count": 9,
	"The Winter Bloom": 4,
	"Timira the Many-Headed": 12,
	"Trollwut": 13,
	"Ungreez": 7,
	"Urmahlullu the Weakened": 4,
	"Utua Stone Sting": 5,
	"Webster": 6,
	"Yirkas Blue Scales": 5,
	"abyssal calamary": 19,
	"acid blob": 1338,
	"acolyte of the cult": 7552,
	"adept of the cult": 7119,
	"adventurer": 136,
	"agrestic chicken": 8,
	"amazon": 11341,
	"ancient scarab": 17670,
	"angry demon": 2,
	"arachnophobica": 14020,
	"arctic faun": 65,
	"askarak demon": 259,
	"assassin": 2138,
	"azure frog": 254,
	"badger": 6951,
	"bandit": 1584,
	"banshee": 843,
	"barbarian bloodwalker": 2018,
	"barbarian brutetamer": 1932,
	"barbarian headsplitter": 4208,
	"barbarian skullhunter": 3520,
	"barkless devotee": 887,
	"barkless fanatic": 404,
	"bat": 3801,
	"bear": 1127,
	"behemoth": 491,
	"black cobra": 1,
	"black sheep": 51,
	"black sphinx acolyte": 2,
	"blood beast": 5501,
	"blood crab": 7160,
	"blood hand": 26,
	"blood priest": 705,
	"blue djinn": 565,
	"bluebeak": 1876,
	"boar": 123,
	"bog frog": 3,
	"bog raider": 4558,
	"bonebeast": 18806,
	"bonelord": 6261,
	"boogy": 1325,
	"braindeath": 722,
	"breach brood": 154,
	"brimstone bug": 757,
	"bug": 3224,
	"burster spectre": 15702,
	"butterfly": 265,
	"carniphila": 3112,
	"carnivorous butterfly": 510,
	"carrion worm": 1165,
	"cat": 583,
	"cave devourer": 987,
	"cave hydra": 12,
	"cave parrot": 304,
	"cave rat": 2282,
	"centipede": 2959,
	"chakoya toolshaper": 114,
	"chakoya tribewarden": 260,
	"chakoya windcaller": 46,
	"charger": 389,
	"chicken": 2048,
	"choking fear": 482,
	"clay guardian": 3005,
	"clomp": 340,
	"cobra assassin": 3952,
	"cobra scout": 2313,
	"cobra vizier": 496,
	"cobra": 3149,
	"coral frog": 154,
	"corrupt naga": 25,
	"corrupted ghost": 993,
	"corrupted skeleton": 1012,
	"corym charlatan": 14490,
	"corym skirmisher": 11733,
	"corym vanguard": 3715,
	"crab": 1802,
	"crawler": 637,
	"crazed beggar": 1145,
	"crazed summer rearguard": 1099,
	"crazed summer vanguard": 949,
	"crazed winter rearguard": 1887,
	"crazed winter vanguard": 1935,
	"crimson frog": 244,
	"crocodile": 10311,
	"crustacea gigantica": 1,
	"crypt shambler": 9299,
	"crypt warden": 1785,
	"crypt warrior": 21,
	"crystal spider": 4445,
	"crystalcrusher": 2094,
	"cult believer": 7101,
	"cult enforcer": 2211,
	"cult scholar": 776,
	"cunning werepanther": 6095,
	"cursed ape": 2282,
	"cyclops": 11159,
	"cyclops drone": 2621,
	"cyclops smith": 1790,
	"damaged worker golem": 602,
	"dark apprentice": 2018,
	"dark faun": 2648,
	"dark magician": 1517,
	"dark monk": 2427,
	"dawnfire asura": 1438,
	"death blob": 2860,
	"deathling scout": 92,
	"deepling guard": 14,
	"deepling scout": 931,
	"deepling spellsinger": 30,
	"deepling warrior": 86,
	"deepsea blood crab": 1423,
	"deepworm": 2000,
	"deer": 378,
	"demon skeleton": 10272,
	"demon": 1,
	"depolarized crackler": 12,
	"desperate white deer": 70,
	"devourer": 2594,
	"diamond servant": 68,
	"diremaw": 5268,
	"dog": 264,
	"domestikion": 1,
	"dragon hatchling": 2223,
	"dragon lord hatchling": 893,
	"dragon lord": 6223,
	"dragon": 19169,
	"draken spellweaver": 40,
	"draken warmaster": 57,
	"dread intruder": 168,
	"drillworm": 838,
	"dromedary": 321,
	"dwarf geomancer": 65,
	"dwarf guard": 3041,
	"dwarf henchman": 301,
	"dwarf soldier": 3352,
	"dwarf": 2453,
	"dworc fleshhunter": 2511,
	"dworc venomsniper": 2639,
	"dworc voodoomaster": 771,
	"earth elemental": 5705,
	"efreet": 60,
	"elder bonelord": 875,
	"elder forest fury": 32,
	"elder mummy": 10,
	"elder wyrm": 1436,
	"elephant": 291,
	"elf arcanist": 2606,
	"elf overseer": 3,
	"elf scout": 4374,
	"elf": 3713,
	"emerald damselfly": 3175,
	"energized raging mage": 2,
	"energy elemental": 1092,
	"enfeebled silencer": 3032,
	"enlightened of the cult": 2289,
	"enraged bookworm": 1,
	"enraged crystal golem": 70,
	"enraged squirrel": 20,
	"enraged white deer": 12,
	"eternal guardian": 86,
	"execowtioner": 4,
	"exotic bat": 11437,
	"exotic cave spider": 4094,
	"falcon knight": 4,
	"falcon paladin": 2,
	"faun": 1750,
	"feral sphinx": 3,
	"feral werecrocodile": 1,
	"filth toad": 14,
	"fire devil": 87,
	"fire elemental": 412,
	"firestarter": 98,
	"fish": 2,
	"flamingo": 81,
	"forest fury": 915,
	"fox": 5685,
	"frazzlemaw": 2102,
	"frost dragon hatchling": 3148,
	"frost dragon": 4973,
	"frost flower asura": 697,
	"frost giantess": 468,
	"frost giant": 584,
	"frost troll": 398,
	"fury": 323,
	"furious troll": 118,
	"gang member": 1570,
	"gargoyle": 8918,
	"gazer spectre": 14035,
	"gazer": 2534,
	"ghastly dragon": 376,
	"ghost wolf": 800,
	"ghost": 9597,
	"ghoulish hyaena": 434,
	"ghoul": 23263,
	"giant spider": 3574,
	"gladiator": 1545,
	"gloom wolf": 2646,
	"glooth anemone": 14,
	"glooth bandit": 6818,
	"glooth blob": 7011,
	"glooth brigand": 6957,
	"glooth golem": 10,
	"gnarlhound": 1223,
	"goblin assassin": 352,
	"goblin leader": 24,
	"goblin scavenger": 773,
	"goblin": 1888,
	"golden servant": 214,
	"gozzler": 699,
	"grave guard": 1,
	"grave robber": 3,
	"gravedigger": 37,
	"greater energy elemental": 8,
	"greater fire elemental": 8,
	"green djinn": 227,
	"green frog": 100,
	"grim reaper": 6611,
	"haunted treeling": 2303,
	"hellspawn": 1723,
	"hero": 7023,
	"hibernal moth": 196,
	"high voltage elemental": 231,
	"hoodinion": 1,
	"humongous fungus": 31,
	"hunter": 2234,
	"husky": 19,
	"hyaena": 991,
	"hydra": 1843,
	"ice golem": 4820,
	"ice witch": 549,
	"iks ahpututu": 2,
	"iks aucar": 8061,
	"iks chuka": 6849,
	"iks churrascan": 93,
	"iks pututu": 5776,
	"iks yapunac": 832,
	"infernalist": 4,
	"insane siren": 473,
	"insect swarm": 90,
	"insectoid worker": 756,
	"instable breach brood": 70,
	"instable sparkion": 64,
	"iron servant": 275,
	"island troll": 1241,
	"jellyfish": 1,
	"jungle moa": 1,
	"killer caiman": 1755,
	"kongra": 4020,
	"lacewing moth": 40,
	"lamassu": 1505,
	"lancer beetle": 557,
	"larva": 22150,
	"leaf golem": 783,
	"lesser swarmer": 116,
	"lich": 841,
	"lion hydra": 2118,
	"lion": 477,
	"lizard chosen": 4570,
	"lizard dragon priest": 230,
	"lizard high guard": 1019,
	"lizard legionnaire": 975,
	"lizard magistratus": 4,
	"lizard sentinel": 2540,
	"lizard snakecharmer": 1115,
	"lizard templar": 2936,
	"lizard zaogun": 64,
	"lost basher": 72,
	"lost exile": 4,
	"lost gnome": 4,
	"lost husher": 38,
	"lost thrower": 52,
	"mad scientist": 469,
	"makara": 2950,
	"mammoth": 3491,
	"manticore": 3,
	"marid": 108,
	"marsh stalker": 2848,
	"massive earth elemental": 207,
	"massive fire elemental": 15,
	"massive water elemental": 50,
	"mearidion": 4,
	"mechanical fighter": 146,
	"medusa": 484,
	"mercury blob": 3285,
	"merlkin": 1413,
	"metal gargoyle": 23,
	"midnight asura": 1641,
	"minotaur amazon": 4,
	"minotaur archer": 3486,
	"minotaur cult follower": 188,
	"minotaur cult prophet": 53,
	"minotaur cult zealot": 49,
	"minotaur guard": 5246,
	"minotaur hunter": 3582,
	"minotaur mage": 2270,
	"minotaur": 9327,
	"mitmah scout": 412,
	"mitmah seer": 140,
	"modified gnarlhound": 1,
	"mole": 14,
	"monk": 361,
	"mooh'tah warrior": 4208,
	"moohtant": 6,
	"muglex clan assassin": 1429,
	"muglex clan feetman": 2403,
	"mummy": 16898,
	"murmillion": 3,
	"mushroom sniffer": 57,
	"mutated bat": 3248,
	"mutated human": 10512,
	"mutated rat": 7093,
	"mutated tiger": 6795,
	"naga archer": 2061,
	"naga warrior": 3679,
	"necromancer": 6575,
	"nightmare scion": 7752,
	"nightmare": 1215,
	"nightstalker": 873,
	"noble lion": 527,
	"nomad": 13448,
	"novice of the cult": 7211,
	"nymph": 4249,
	"ogre brute": 325,
	"ogre savage": 141,
	"ogre shaman": 241,
	"omnivora": 271,
	"orc berserker": 4493,
	"orc cult fanatic": 511,
	"orc cult inquisitor": 892,
	"orc cult minion": 1065,
	"orc cult priest": 359,
	"orc cultist": 342,
	"orc leader": 802,
	"orc marauder": 165,
	"orc rider": 448,
	"orc shaman": 1905,
	"orc spearman": 3001,
	"orc warlord": 225,
	"orc warrior": 4095,
	"orchid frog": 152,
	"orclops doomhauler": 605,
	"orclops ravager": 562,
	"orc": 2417,
	"overcharge": 18,
	"panda": 212,
	"parder": 5,
	"parrot": 11,
	"penguin": 1426,
	"phantasm": 8,
	"pigeon": 164,
	"pig": 77,
	"pirat bombardier": 3534,
	"pirat cutthroat": 7783,
	"pirat mate": 2707,
	"pirat scoundrel": 3536,
	"pirate buccaneer": 2348,
	"pirate corsair": 589,
	"pirate cutthroat": 3600,
	"pirate ghost": 100,
	"pirate marauder": 6271,
	"pirate skeleton": 284,
	"pixie": 4303,
	"poacher": 2319,
	"poison spider": 13737,
	"polar bear": 1095,
	"pooka": 1455,
	"priestess": 268,
	"priestess of the wild sun": 5,
	"putrid mummy": 415,
	"quara constrictor scout": 1944,
	"quara constrictor": 2575,
	"quara hydromancer scout": 3500,
	"quara hydromancer": 2590,
	"quara mantassin scout": 5257,
	"quara mantassin": 2236,
	"quara pincher scout": 4686,
	"quara pincher": 4733,
	"quara predator scout": 2420,
	"quara predator": 3530,
	"rabbit": 654,
	"rabid wolves": 989,
	"ragged rabid wolves": 303,
	"rat": 1419,
	"ravenous lava lurker": 7436,
	"reality reavers": 181,
	"renegade knight": 8372,
	"retching horror": 813,
	"ripper spectre": 10260,
	"roaring lion": 8001,
	"rogue naga": 20,
	"rorc": 557,
	"rot elemental": 4679,
	"rotworm": 5886,
	"rustheap golem": 22,
	"sacred spider": 268,
	"salamander": 1374,
	"sandcrawler": 1586,
	"sandstone scorpion": 7,
	"scarab": 9018,
	"scissorion": 4,
	"scorpion": 6938,
	"sea serpent": 1914,
	"seacrest serpent": 859,
	"seagull": 47,
	"serpent spawn": 825,
	"shaburak demon": 8666,
	"shaburak lord": 447,
	"shadow pupil": 154,
	"shark": 212,
	"sheep": 150,
	"shock head": 272,
	"sibang": 4200,
	"silencer": 1086,
	"silver rabbit": 164,
	"skeleton warrior": 806,
	"skeleton": 11519,
	"skunk": 422,
	"slime": 3980,
	"slug": 78,
	"smuggler": 2271,
	"snake": 4032,
	"solitary frost dragon": 4,
	"soul-broken harbinger": 638,
	"souleater": 2098,
	"sparkion": 219,
	"spark of destruction": 61,
	"sphinx": 3503,
	"spider": 2978,
	"spit nettle": 408,
	"spitter": 4,
	"spyrat": 80,
	"squidgy slime": 812,
	"squirrel": 1168,
	"stalker": 7480,
	"stone golem": 3113,
	"stonerefiner": 8963,
	"strange slime": 3,
	"swamp troll": 7858,
	"swampling": 1684,
	"swan maiden": 1197,
	"swarmer hatchling": 1,
	"swarmer": 910,
	"tainted soul": 108,
	"tarantula": 18386,
	"tarnished spirit": 39,
	"terramite": 6801,
	"terrified elephant": 267,
	"terror bird": 716,
	"thanatursus": 1125,
	"thief": 1,
	"thieving squirrel": 4,
	"thornback tortoise": 8720,
	"tiger": 217,
	"toad": 1690,
	"tomb servant": 466,
	"tormented ghost": 41,
	"tortoise": 14051,
	"troll champion": 351,
	"troll legionnaire": 88,
	"troll": 1559,
	"tunnel tyrant": 1431,
	"twisted pooka": 2635,
	"undead cavebear": 3,
	"undead gladiator": 8566,
	"undead mine worker": 5,
	"undead prospector": 2,
	"usurper archer": 58,
	"valkyrie": 6656,
	"vampire bride": 3224,
	"vampire viscount": 1766,
	"vampire": 9939,
	"vicious lich": 9,
	"vicious squire": 15112,
	"vile destroyer": 8,
	"vile grandmaster": 3933,
	"vulcongra": 52,
	"wailing widow": 820,
	"war golem": 40,
	"war wolf": 19001,
	"warlock": 17,
	"waspoid": 207,
	"wasp": 5183,
	"water buffalo": 62,
	"water elemental": 17025,
	"weakened frazzlemaw": 4788,
	"werebadger": 7143,
	"werebear": 3047,
	"wereboar": 4557,
	"werecrocodile": 2,
	"werefox": 4502,
	"werehyaena shaman": 8425,
	"werehyaena": 22465,
	"werelioness": 3605,
	"werelion": 3204,
	"werepanther": 8,
	"weretiger": 3465,
	"werewolf": 2654,
	"white deer": 89,
	"white lion": 1195,
	"white shade": 4,
	"white tiger": 6,
	"white weretiger": 2045,
	"wiggler": 685,
	"wild warrior": 2684,
	"wilting leaf golem": 1239,
	"winter wolf": 1918,
	"wisp": 219,
	"witch": 2816,
	"wolf": 4400,
	"worker golem": 1742,
	"worm priestess": 4374,
	"wyrm": 18005,
	"wyvern": 2606,
	"yielothax": 2139,
	"young goanna": 1,
	"young sea serpent": 1959,
	"young troll": 45,
	"zombie": 4191
}
