{
	"Abyssador": 1,
	"Aftershock": 3,
	"Ahau": 22,
	"Alptramun": 1,
	"Amenef the Burning": 5,
	"Anomaly": 14,
	"Arbaziloth": 3,
	"Ascending Ferumbras": 1,
	"Atab": 1,
	"Baron Brute": 1,
	"Bibby Bloodbath": 18,
	"Black Knight": 8,
	"Black Vixen": 46,
	"Bloodback": 41,
	"Bone Capsule": 4,
	"Boogey": 2,
	"Boreth": 1,
	"Bragrumol": 3,
	"Brokul": 4,
	"Brother Chill": 1,
	"Brother Freeze": 1,
	"Brother Worm": 1,
	"Bruton": 11,
	"Cave Spider": 2,
	"Coldheart": 1,
	"Count Vlarkorth": 7,
	"Crultor": 11,
	"Custodian": 1,
	"Damage Resonance": 5,
	"Darakan the Executioner": 1,
	"Darkfang": 41,
	"Dazed Leaf Golem": 8,
	"Deathbine": 1,
	"Deathbringer": 1,
	"Deathstrike": 1,
	"Demodras": 1,
	"Despair": 8,
	"Despor": 11,
	"Destabilized Ferumbras": 1,
	"Dharalion": 1,
	"Dirtbeard": 4,
	"Diseased Bill": 8,
	"Diseased Dan": 8,
	"Diseased Fred": 8,
	"Doctor Perhaps": 4,
	"Doomhowl": 1,
	"Dorokoll the Mystic": 1,
	"Dragon Pack": 10,
	"Dreadwing": 1,
	"Drume": 76,
	"Duke Krule": 7,
	"Earl Osam": 8,
	"Ekatrix": 2,
	"Eliz the Unyielding": 1,
	"Eradicator": 14,
	"Eshtaba the Conjurer": 1,
	"Essence of Malice": 1,
	"Ethershreck": 7,
	"Evil Mastermind": 2,
	"Faceless Bane": 12,
	"Fallen Mooh'Tah Master Ghar": 1,
	"Fatality": 1,
	"Ferumbras": 1,
	"Ferumbras Soul Splinter": 8,
	"Foreshock": 3,
	"Fugue": 1,
	"Ghulosh": 1,
	"Glitterscale": 3,
	"Gnomevil": 1,
	"Gnorre Chyllson": 1,
	"Gorga": 1,
	"Gorgo": 1,
	"Gorzindel": 2,
	"Gralvalon": 4,
	"Grand Canon Dominus": 25,
	"Grand Chaplain Gaunder": 17,
	"Grand Commander Soeren": 24,
	"Grand Master Oberon": 46,
	"Greedok": 11,
	"Guard Captain Quaid": 7,
	"Hairman the Huge": 1,
	"Haunter": 1,
	"Heoni": 31,
	"Hide": 1,
	"Ichgahal": 1,
	"Incineron": 1,
	"Inky": 1,
	"Irgix the Flimsy": 7,
	"Jailer": 56,
	"Katex Blood Tongue": 47,
	"King Zelos": 1,
	"Kroazur": 27,
	"Kusuma": 7,
	"Leiden": 4,
	"Lersatio": 1,
	"Lethal Lissy": 1,
	"Lizard Gate Guardian": 1,
	"Lloyd": 2,
	"Lokathmor": 1,
	"Lord Azaram": 6,
	"Magma Bubble": 13,
	"Maliz": 11,
	"Malkhar Deathbringer": 1,
	"Malvaroth": 1,
	"Marziel": 1,
	"Mazoran": 1,
	"Mazzinor": 2,
	"Megasylvan Yselda": 2,
	"Menace": 1,
	"Mephiles": 2,
	"Mezlon the Defiler": 1,
	"Mitmah Vanguard": 5,
	"Monstor": 2,
	"Morik the Gladiator": 2,
	"Neferi the Spy": 6,
	"Norgle Glacierbeard": 1,
	"Obujos": 4,
	"Outburst": 15,
	"Plagirath": 1,
	"Preceptor Lazare": 44,
	"Rage of Mazoran": 23,
	"Ragiaz": 1,
	"Ratmiral Blackwhiskers": 2,
	"Ravenous Hunger": 4,
	"Raxias": 2,
	"Razzagorn": 1,
	"Realityquake": 3,
	"Renegade Orc": 1,
	"Rocko": 1,
	"Rottie the Rotworm": 1,
	"Rotworm Queen": 1,
	"Rukor Zad": 1,
	"Rupture": 1,
	"Scarlett Etzel": 88,
	"Shadowpelt": 44,
	"Shard of Corruption": 1,
	"Shardhead": 1,
	"Sharpclaw": 41,
	"Sharptooth": 1,
	"Shlorg": 1,
	"Shulgrax": 1,
	"Sir Baeloc": 7,
	"Sir Nictros": 7,
	"Sir Valorcrest": 1,
	"Sister Hetai": 7,
	"Splasher": 1,
	"Srezz Yellow Eyes": 47,
	"Sugar Daddy": 19,
	"Svoren the Mad": 1,
	"Tarbaz": 1,
	"Tentugly": 3,
	"Thawing Dragon Lord": 5,
	"The Armored Voidborn": 1,
	"The Axeorcist": 1,
	"The Blazing Rose": 2,
	"The Bloodtusk": 1,
	"The Brainstealer": 4,
	"The Diamond Blossom": 2,
	"The Dread Maiden": 1,
	"The Dreadorian": 1,
	"The End of Days": 84,
	"The Evil Eye": 1,
	"The False God": 1,
	"The Fear Feaster": 1,
	"The Flaming Orchid": 6,
	"The Keeper": 1,
	"The Lily of Night": 2,
	"The Masked Marauder": 1,
	"The Monster": 1,
	"The Moonlight Aster": 5,
	"The Nightmare Beast": 1,
	"The Noxious Spawn": 1,
	"The Obliverator": 1,
	"The Pale Worm": 1,
	"The Pit Lord": 1,
	"The Sandking": 1,
	"The Scourge of Oblivion": 1,
	"The Sinister Hermit": 1,
	"The Snapper": 2,
	"The Souldespoiler": 1,
	"The Spellstealer": 1,
	"The Unarmored Voidborn": 1,
	"The Unwelcome": 1,
	"The Weakened Count": 1,
	"The Winter Bloom": 5,
	"Timira the Many-Headed": 38,
	"Tiquandas Revenge": 1,
	"Tirecz": 1,
	"Tormentor": 1,
	"Tremorak": 1,
	"Trollwut": 31,
	"Twisterror": 4,
	"Unaz the Mean": 7,
	"Ungreez": 3,
	"Urmahlullu the Weakened": 4,
	"Ushuriel": 1,
	"Utua Stone Sting": 47,
	"Vashresamun": 2,
	"Vengar": 11,
	"Versperoth": 1,
	"Vilear": 10,
	"Vok the Freakish": 7,
	"Webster": 1,
	"White Pale": 1,
	"Yirkas Blue Scales": 47,
	"Zamulosh": 1,
	"Zugurosh": 1,
	"abyssal calamary": 22,
	"acid blob": 153,
	"acolyte of the cult": 3434,
	"adept of the cult": 4397,
	"adult goanna": 164,
	"adventurer": 103,
	"afflicted strider": 32,
	"albino dragon": 2,
	"amazon": 6276,
	"ancient lion knight": 58,
	"ancient scarab": 2401,
	"angry adventurer": 2,
	"animated feather": 782,
	"animated moohtant": 1,
	"animated skunk": 2,
	"arachnophobica": 5971,
	"arctic faun": 1,
	"armadile": 12,
	"askarak demon": 127,
	"askarak lord": 6,
	"assassin": 611,
	"azure frog": 97,
	"badger": 2644,
	"bandit": 564,
	"banshee": 57,
	"barbarian bloodwalker": 124,
	"barbarian brutetamer": 102,
	"barbarian headsplitter": 291,
	"barbarian skullhunter": 237,
	"barkless devotee": 875,
	"barkless fanatic": 553,
	"bashmu": 782,
	"bat": 2001,
	"bear": 458,
	"behemoth": 477,
	"berserker chicken": 50,
	"betrayed wraith": 1576,
	"biting book": 128,
	"black sheep": 8,
	"black sphinx acolyte": 178,
	"blemished spawn": 111,
	"blightwalker": 849,
	"blood beast": 1439,
	"blood crab": 1539,
	"blood hand": 10,
	"blood priest": 212,
	"blue djinn": 105,
	"boar man": 1739,
	"boar": 98,
	"bog frog": 35,
	"bog raider": 791,
	"bonebeast": 2962,
	"bonelord": 802,
	"boogy": 437,
	"brain squid": 532,
	"braindeath": 191,
	"branchy crawler": 357,
	"breach brood": 13694,
	"brimstone bug": 412,
	"brinebrute inferniarch": 354,
	"brittle skeleton": 63,
	"broken shaper": 176,
	"broodrider inferniarch": 4783,
	"bug": 1188,
	"bulltaur alchemist": 4924,
	"bulltaur brute": 6090,
	"bulltaur forgepriest": 4999,
	"burning book": 2052,
	"burning gladiator": 551,
	"burster spectre": 5861,
	"butterfly": 131,
	"calamary": 56,
	"candy horror": 1034,
	"carniphila": 245,
	"carnisylvan sapling": 114,
	"carnivorous butterfly": 142,
	"carnivostrich": 1026,
	"carrion worm": 442,
	"cat": 141,
	"cave chimera": 163,
	"cave devourer": 462,
	"cave hydra": 18,
	"cave rat": 1469,
	"cellar rat": 26,
	"centipede": 884,
	"chakoya toolshaper": 128,
	"chakoya tribewarden": 173,
	"chakoya windcaller": 44,
	"charger": 976,
	"charging Outburst": 58,
	"chasm spawn": 1476,
	"cheeky sugar cube": 96,
	"chicken": 423,
	"chocolate blob": 1,
	"choking fear": 8042,
	"clay guardian": 250,
	"cliff strider": 15,
	"clomp": 82,
	"cobra assassin": 3375,
	"cobra scout": 1913,
	"cobra vizier": 787,
	"cobra": 1526,
	"containment machine": 1,
	"coral frog": 66,
	"corrupt naga": 351,
	"corym charlatan": 1923,
	"corym skirmisher": 1464,
	"corym vanguard": 668,
	"cosmic energy prism A": 2,
	"cosmic energy prism B": 2,
	"cosmic energy prism C": 2,
	"cosmic energy prism D": 2,
	"crab": 465,
	"crape man": 3736,
	"crawler": 1943,
	"crazed beggar": 158,
	"crazed dwarf": 44,
	"crazed summer rearguard": 3061,
	"crazed summer vanguard": 2690,
	"crazed winter rearguard": 1277,
	"crazed winter vanguard": 1306,
	"crimson frog": 87,
	"crocodile": 1323,
	"crypt defiler": 115,
	"crypt shambler": 2358,
	"crypt warden": 987,
	"crypt warrior": 353,
	"crystal spider": 71,
	"crystalcrusher": 399,
	"cult believer": 640,
	"cult enforcer": 157,
	"cult scholar": 33,
	"cunning werepanther": 1058,
	"cursed ape": 185,
	"cyclops": 4434,
	"cyclops drone": 1089,
	"cyclops smith": 869,
	"damaged crystal golem": 1,
	"damaged worker golem": 104,
	"damned soul": 13,
	"dark apprentice": 319,
	"dark carnisylvan": 236,
	"dark faun": 826,
	"dark magician": 189,
	"dark monk": 576,
	"dark torturer": 5104,
	"dawn bat": 49,
	"dawnfire asura": 5647,
	"dawnfly": 721,
	"death blob": 614,
	"death dragon": 1,
	"deathling scout": 375,
	"deathling spellsinger": 208,
	"deepling brawler": 45,
	"deepling elite": 8,
	"deepling guard": 70,
	"deepling master librarian": 4,
	"deepling scout": 544,
	"deepling spellsinger": 94,
	"deepling tyrant": 9,
	"deepling warrior": 92,
	"deepling worker": 403,
	"deepsea blood crab": 114,
	"deepworm": 1734,
	"deer": 432,
	"defiler": 550,
	"demon outcast": 1811,
	"demon parrot": 18,
	"demon skeleton": 1628,
	"demon": 1676,
	"depolarized crackler": 12,
	"desperate white deer": 49,
	"destroyer": 1657,
	"devourer": 1465,
	"diamond servant replica": 55,
	"dire penguin": 2,
	"diremaw": 3786,
	"disgusting ooze": 12,
	"dog": 93,
	"domestikion": 216,
	"doom deer": 59,
	"dragolisk": 9587,
	"dragon hatchling": 2125,
	"dragon lord hatchling": 102,
	"dragon lord": 978,
	"dragon": 3313,
	"draken abomination": 76,
	"draken elite": 63,
	"draken spellweaver": 2334,
	"draken warmaster": 2851,
	"dread intruder": 11333,
	"dread minion": 28,
	"drillworm": 870,
	"dromedary": 159,
	"dwarf geomancer": 141,
	"dwarf guard": 563,
	"dwarf miner": 23,
	"dwarf soldier": 747,
	"dwarf": 572,
	"dworc fleshhunter": 665,
	"dworc venomsniper": 835,
	"dworc voodoomaster": 518,
	"earth elemental": 249,
	"efreet": 8,
	"elder bonelord": 260,
	"elder forest fury": 35,
	"elder wyrm": 378,
	"elephant": 71,
	"elf arcanist": 872,
	"elf scout": 1609,
	"elf": 1151,
	"emerald damselfly": 1800,
	"emerald tortoise": 40,
	"energetic book": 363,
	"energuardian of tales": 417,
	"energy elemental": 1091,
	"enfeebled silencer": 5137,
	"enlightened of the cult": 1775,
	"enraged crystal golem": 206,
	"enraged squirrel": 4,
	"enraged white deer": 11,
	"enslaved dwarf": 7,
	"enthralled demon": 81,
	"eruption of destruction": 44,
	"eternal guardian": 1892,
	"evil sheep": 103,
	"evil sheep lord": 15,
	"exotic bat": 6488,
	"exotic cave spider": 2824,
	"eyeless devourer": 54,
	"falcon knight": 4356,
	"falcon paladin": 2740,
	"faun": 120,
	"feral sphinx": 89,
	"feral werecrocodile": 101,
	"feversleep": 494,
	"fire devil": 98,
	"fire elemental": 1985,
	"firestarter": 759,
	"fish": 58,
	"flamingo": 71,
	"flimsy lost soul": 3821,
	"floating savant": 3,
	"flying book": 4,
	"foam stalker": 1093,
	"forest fury": 1739,
	"fox": 2384,
	"frazzlemaw": 12404,
	"freakish lost soul": 11,
	"frost dragon hatchling": 217,
	"frost dragon": 342,
	"frost flower asura": 1005,
	"frost giantess": 9,
	"frost giant": 10,
	"frost troll": 148,
	"fruit drop": 5,
	"fury": 2168,
	"furious fire elemental": 8,
	"furious troll": 9,
	"gang member": 184,
	"gargoyle": 1062,
	"gazer spectre": 5528,
	"gazer": 166,
	"ghastly dragon": 879,
	"ghost": 1955,
	"ghoul": 6860,
	"giant spider": 1585,
	"girtablilu warrior": 5599,
	"gladiator": 280,
	"gloom wolf": 291,
	"glooth anemone": 45,
	"glooth bandit": 2003,
	"glooth blob": 2408,
	"glooth brigand": 2085,
	"glooth golem": 788,
	"gnarlhound": 523,
	"goblin assassin": 61,
	"goblin scavenger": 77,
	"goblin": 651,
	"golden servant replica": 56,
	"gore horn": 43,
	"gorerilla": 30,
	"gorger inferniarch": 4021,
	"gozzler": 146,
	"grave robber": 165,
	"gravedigger": 43,
	"greater energy elemental": 10,
	"greater fire elemental": 12,
	"green djinn": 22,
	"green frog": 21,
	"grim reaper": 5748,
	"grimeleech": 2964,
	"guardian of tales": 615,
	"guzzlemaw": 4201,
	"hand of cursed fate": 1060,
	"hardened usurper archer": 75,
	"hardened usurper knight": 143,
	"hardened usurper warlock": 161,
	"harpy": 2306,
	"haunted treeling": 341,
	"hellfire fighter": 2630,
	"hellflayer": 2168,
	"hellhound": 2356,
	"hellhunter inferniarch": 6501,
	"hellspawn": 4431,
	"hero": 2027,
	"hibernal moth": 70,
	"hideous fungus": 105,
	"high voltage elemental": 189,
	"honey elemental": 181,
	"honour guard": 622,
	"hoodinion": 179,
	"hot dog": 21,
	"hulking carnisylvan": 255,
	"hulking prehemoth": 41,
	"humongous fungus": 357,
	"humorless fungus": 44,
	"hunger worm": 2,
	"hunter": 714,
	"husky": 53,
	"hyaena": 492,
	"hydra": 2215,
	"ice golem": 615,
	"ice witch": 130,
	"icecold book": 919,
	"iks ahpututu": 8,
	"iks aucar": 205,
	"iks chuka": 174,
	"iks churrascan": 40,
	"iks pututu": 165,
	"iks yapunac": 5076,
	"infected weeper": 7,
	"infernal frog": 26,
	"infernalist": 1,
	"ink blob": 285,
	"insane siren": 1088,
	"insect swarm": 160,
	"insectoid worker": 1621,
	"iron servant replica": 83,
	"ironblight": 25,
	"island troll": 516,
	"jellyfish": 47,
	"juggernaut": 129,
	"jungle moa": 37,
	"juvenile bashmu": 1118,
	"killer caiman": 251,
	"killer rabbit": 62,
	"knowledge elemental": 162,
	"knowledge raider": 145,
	"kongra": 3700,
	"lacewing moth": 102,
	"lamassu": 163,
	"lancer beetle": 199,
	"larva": 3797,
	"lava golem": 15,
	"lava lurker attendant": 4,
	"lava lurker": 7,
	"lavafungus": 2107,
	"lavaworm": 2454,
	"leaf golem": 774,
	"lesser fire devil": 4,
	"lesser swarmer": 653,
	"lich": 183,
	"liodile": 1564,
	"lion archer": 48,
	"lion commander": 23,
	"lion knight": 19,
	"lion warlock": 160,
	"lion": 175,
	"little corym charlatan": 23,
	"lizard chosen": 1618,
	"lizard dragon priest": 447,
	"lizard high guard": 2878,
	"lizard legionnaire": 1289,
	"lizard magistratus": 6,
	"lizard noble": 6,
	"lizard sentinel": 1111,
	"lizard snakecharmer": 529,
	"lizard templar": 1211,
	"lizard zaogun": 668,
	"lost basher": 36,
	"lost berserker": 44,
	"lost exile": 23,
	"lost husher": 12,
	"lost soul": 1227,
	"lost thrower": 55,
	"lumbering carnivor": 5499,
	"mad scientist": 85,
	"magical sphere": 61,
	"magma crawler": 27,
	"magma crystal": 42,
	"makara": 2001,
	"makeshift home": 7,
	"mammoth": 1111,
	"manticore": 85,
	"marsh stalker": 1130,
	"massive earth elemental": 130,
	"massive energy elemental": 3,
	"massive fire elemental": 62,
	"massive water elemental": 19,
	"meadow strider": 519,
	"mean lost soul": 1557,
	"meandering mushroom": 1028,
	"mearidion": 299,
	"mechanical fighter": 3,
	"medusa": 2923,
	"mega dragon": 3471,
	"menacing carnivor": 631,
	"mercury blob": 183,
	"merlkin": 1564,
	"metal gargoyle": 422,
	"midnight asura": 5549,
	"minotaur archer": 1371,
	"minotaur bruiser": 138,
	"minotaur cult follower": 1146,
	"minotaur cult prophet": 365,
	"minotaur cult zealot": 226,
	"minotaur guard": 1771,
	"minotaur hunter": 358,
	"minotaur idol": 12,
	"minotaur invader": 3,
	"minotaur mage": 681,
	"minotaur poacher": 24,
	"minotaur": 3709,
	"mint drop": 90,
	"mitmah scout": 2599,
	"mitmah seer": 934,
	"modified gnarlhound": 34,
	"mole": 142,
	"monk": 304,
	"mooh'tah warrior": 375,
	"mould phantom": 219,
	"mountain troll": 4648,
	"muglex clan assassin": 32,
	"muglex clan feetman": 43,
	"muglex clan scavenger": 26,
	"mummy": 3987,
	"murmillion": 462,
	"museum stone golem": 1,
	"museum stone rhino": 1,
	"mushroom sniffer": 19,
	"mutated bat": 968,
	"mutated human": 610,
	"mutated rat": 720,
	"mutated tiger": 3948,
	"mystic energy": 2,
	"naga archer": 1383,
	"naga warrior": 2476,
	"necromancer": 337,
	"neutral deepling warrior": 17,
	"nibblemaw": 1538,
	"nightmare scion": 1069,
	"nightmare": 243,
	"nightstalker": 9,
	"noble lion": 77,
	"nomad": 2771,
	"northern pike": 5,
	"novice of the cult": 1551,
	"nymph": 463,
	"ogre brute": 35,
	"ogre savage": 17,
	"ogre shaman": 20,
	"omnivora": 219,
	"oozing carcass": 1223,
	"orc berserker": 1495,
	"orc cult fanatic": 142,
	"orc cult inquisitor": 361,
	"orc cult minion": 297,
	"orc cult priest": 198,
	"orc cultist": 196,
	"orc leader": 755,
	"orc marauder": 5,
	"orc rider": 169,
	"orc shaman": 2542,
	"orc spearman": 1341,
	"orc warlord": 101,
	"orc warrior": 1885,
	"orchid frog": 58,
	"orclops doomhauler": 15,
	"orc": 1178,
	"orewalker": 22,
	"overcharged demon": 6,
	"overcharge": 85,
	"panda": 26,
	"parasite": 8,
	"parder": 80,
	"parrot": 10,
	"party skeleton": 12,
	"penguin": 612,
	"phantasm": 215,
	"pigeon": 105,
	"pig": 186,
	"pirat bombardier": 5616,
	"pirat cutthroat": 10291,
	"pirat mate": 6145,
	"pirat scoundrel": 5533,
	"pirate buccaneer": 874,
	"pirate corsair": 376,
	"pirate cutthroat": 1692,
	"pirate ghost": 7,
	"pirate marauder": 2685,
	"pirate skeleton": 38,
	"pixie": 352,
	"plaguesmith": 2695,
	"poacher": 784,
	"poison spider": 2717,
	"poisonous carnisylvan": 162,
	"polar bear": 309,
	"pooka": 80,
	"priestess": 101,
	"priestess of the wild sun": 426,
	"putrid mummy": 670,
	"quara constrictor scout": 751,
	"quara constrictor": 72,
	"quara hydromancer scout": 683,
	"quara hydromancer": 65,
	"quara kindler": 1,
	"quara mantassin scout": 173,
	"quara mantassin": 45,
	"quara pincher scout": 782,
	"quara pincher": 101,
	"quara predator scout": 823,
	"quara predator": 92,
	"rabbit": 386,
	"rabid wolves": 762,
	"rage squid": 2009,
	"ragged rabid wolves": 224,
	"rat": 664,
	"ravenous lava lurker": 3414,
	"reality reaver": 41,
	"reality reavers": 13183,
	"redeemed soul": 122,
	"renegade knight": 1406,
	"retching horror": 8128,
	"rhindeer": 3665,
	"rift fragment": 3,
	"rift invader": 166,
	"ripper spectre": 2639,
	"roaring lion": 1062,
	"rogue naga": 322,
	"rootthing amber shaper": 648,
	"rootthing bug tracker": 1301,
	"rootthing nutshell": 2367,
	"rorc": 287,
	"rot elemental": 2051,
	"rotten golem": 272,
	"rotten man-maggot": 800,
	"rotworm": 2587,
	"rustheap golem": 804,
	"sabretooth": 40,
	"sacred snake": 16,
	"salamander trainer": 1,
	"salamander": 558,
	"sand brood": 45,
	"sandcrawler": 503,
	"scarab": 1219,
	"scissorion": 481,
	"scorpion": 1385,
	"sea serpent": 541,
	"seacrest serpent": 245,
	"seagull": 56,
	"security golem": 4,
	"serpent spawn": 2521,
	"servant of Tentugly": 26,
	"shaburak demon": 210,
	"shadow pupil": 52,
	"shaper matriarch": 111,
	"shark": 74,
	"sheep": 73,
	"shock head": 636,
	"sibang": 4012,
	"silencer": 9527,
	"silver rabbit": 281,
	"sineater inferniarch": 4559,
	"skeleton elite warrior": 49,
	"skeleton warrior": 137,
	"skeleton": 4365,
	"skunk": 107,
	"slime": 760,
	"slug": 39,
	"smuggler": 630,
	"snake": 2337,
	"solitary frost dragon": 5,
	"son of Verminor": 218,
	"sopping carcass": 613,
	"soul-broken harbinger": 717,
	"souleater": 2685,
	"sparkion": 13565,
	"spark of destruction": 1132,
	"spectre": 260,
	"spellreaper inferniarch": 6647,
	"sphinx": 1203,
	"spider": 1416,
	"spiky carnivor": 5501,
	"spit nettle": 155,
	"spitter": 18,
	"spyrat": 118,
	"squid warden": 732,
	"squidgy slime": 1346,
	"squirrel": 58,
	"stabilizing dread intruder": 372,
	"stabilizing reality reaver": 375,
	"stalker": 1613,
	"stone devourer": 10,
	"stone golem": 317,
	"stone rhino": 5,
	"stonerefiner": 4864,
	"strange rat": 31,
	"strange slime": 1,
	"streaked devourer": 2535,
	"sugar cube worker": 5,
	"sugar cube": 2,
	"swamp troll": 4569,
	"swampling": 1160,
	"swan maiden": 234,
	"swarmer": 1621,
	"symbol of fear": 3,
	"tainted soul": 39,
	"tarantula": 2551,
	"tarnished spirit": 27,
	"terramite": 140,
	"terror bird": 102,
	"terrorsleep": 766,
	"thanatursus": 1207,
	"thieving squirrel": 1,
	"thornback tortoise": 1259,
	"tiger": 86,
	"toad": 462,
	"tormented ghost": 18,
	"tortoise": 1699,
	"toxic swarm": 18,
	"tremendous tyrant": 190,
	"troll champion": 228,
	"troll legionnaire": 18,
	"troll marauder": 1,
	"troll-trained salamander": 2670,
	"troll": 2422,
	"true dawnfire asura": 1049,
	"true frost flower asura": 282,
	"true midnight asura": 1249,
	"truffle worker": 86,
	"tunnel devourer": 13,
	"tunnel tyrant": 616,
	"twisted pooka": 812,
	"twisted shaper": 159,
	"two-headed turtle": 2634,
	"undead dragon": 232,
	"undead elite gladiator": 3,
	"undead gladiator": 1537,
	"unstable spark": 36,
	"usurper archer": 76,
	"usurper commander": 230,
	"usurper knight": 114,
	"usurper warlock": 46,
	"valkyrie": 3110,
	"vampire bride": 948,
	"vampire pig": 58,
	"vampire viscount": 841,
	"vampire": 2294,
	"varnished diremaw": 179,
	"venerable foam stalker": 43,
	"venerable girtablilu": 2434,
	"vermin swarm": 4,
	"vexclaw": 4557,
	"vicious lich": 11,
	"vicious squire": 3458,
	"vile destroyer": 10,
	"vile grandmaster": 795,
	"voidshard": 16,
	"vulcongra": 134,
	"wafer paper butterfly": 1,
	"wailing widow": 166,
	"walker": 16,
	"war golem": 248,
	"war wolf": 3205,
	"wardragon": 8312,
	"warlock": 10,
	"waspoid": 539,
	"wasp": 5268,
	"water buffalo": 42,
	"water elemental": 188,
	"weakened frazzlemaw": 8609,
	"weeper": 24,
	"werebadger": 1593,
	"werebear": 679,
	"wereboar": 958,
	"werecrocodile": 213,
	"werefox": 1533,
	"werehyaena shaman": 5522,
	"werehyaena": 14256,
	"werelioness": 16887,
	"werelion": 15155,
	"werepanther": 391,
	"weretiger": 640,
	"werewolf": 435,
	"white deer": 69,
	"white lion": 6044,
	"white shade": 19,
	"white tiger": 5,
	"white weretiger": 360,
	"wiggler": 386,
	"wild warrior": 584,
	"wilting leaf golem": 1438,
	"winter wolf": 1713,
	"wisp": 66,
	"witch": 726,
	"wolf": 2107,
	"woodling": 669,
	"worker golem": 251,
	"worm priestess": 465,
	"wyrm": 1125,
	"wyvern": 1094,
	"yalahari despoiler": 19,
	"yielothax": 165,
	"young goanna": 172,
	"young sea serpent": 335,
	"young troll": 32,
	"zombie": 49
}
